numpy_serializer/__init__.py
numpy_serializer-0.1.3.dist-info/LICENSE
numpy_serializer-0.1.3.dist-info/METADATA
numpy_serializer-0.1.3.dist-info/WHEEL
numpy_serializer-0.1.3.dist-info/top_level.txt
numpy_serializer-0.1.3.dist-info/RECORD
