Metadata-Version: 2.1
Name: numpy-serializer
Version: 0.1.3
Summary: Preserve numpy arrays shapes while serializing them to bytes
Home-page: https://github.com/4thel00z/numpy-serializer
Author: 4thel00z
Author-email: 4thel00z@gmail.com
License: GPL
Platform: UNKNOWN
Classifier: Programming Language :: Python
Classifier: Programming Language :: Python :: 3.7
Requires-Python: >=3.6
Requires-Dist: msgpack (==1.0.2)
Requires-Dist: msgpack-numpy (==0.4.7.1)
Requires-Dist: numpy (==1.19.4)
